django_sequences_py2-0.2.dist-info/DESCRIPTION.rst
django_sequences_py2-0.2.dist-info/METADATA
django_sequences_py2-0.2.dist-info/RECORD
django_sequences_py2-0.2.dist-info/WHEEL
django_sequences_py2-0.2.dist-info/metadata.json
django_sequences_py2-0.2.dist-info/top_level.txt
sequences/__init__.py
sequences/admin.py
sequences/apps.py
sequences/models.py
sequences/test_postgresql_settings.py
sequences/test_settings.py
sequences/tests.py
sequences/migrations/0001_initial.py
sequences/migrations/__init__.py
