Metadata-Version: 2.0
Name: django-sequences-py2
Version: 0.2
Summary: Forked from augustien's django-sequences, this package aims to maintain py2 compatibility.
Home-page: https://github.com/flocklet/django-sequences-py2
Author: Aymeric Augustin, Flocklet Technologies
Author-email: opensource@flocklet.com
License: BSD
Platform: UNKNOWN
Classifier: Development Status :: 5 - Production/Stable
Classifier: Environment :: Web Environment
Classifier: Framework :: Django
Classifier: Framework :: Django :: 1.8
Classifier: Framework :: Django :: 1.9
Classifier: Framework :: Django :: 1.10
Classifier: Framework :: Django :: 1.11
Classifier: Intended Audience :: Developers
Classifier: License :: OSI Approved :: BSD License
Classifier: Operating System :: OS Independent
Classifier: Programming Language :: Python
Classifier: Programming Language :: Python :: 2
Classifier: Programming Language :: Python :: 2.7
